[
  { "id": 1, "name": "Яблоки", "price": 25, "type": "fruits", "season": ["Лето","Осень","Зима"], "inSeason": true, "method": "Органические", "image": "img/product/istockphoto-478157668-612x612.jpg", "farmer": "Анна Василенко", "farmer_info": "Органические яблоки из Тирасполя", "storage": "Хранить в прохладном месте", "shelf_life": "14 дней", "cooking": "Есть свежими, запекать", "location": "Григориополь" },
  { "id": 2, "name": "Морковь", "price": 10, "type": "vegetables", "season": ["Лето","Осень","Зима"], "inSeason": true, "method": "Органические", "image": "img/product/morkov.jpg", "farmer": "Анна Василенко", "farmer_info": "Свежие корнеплоды с органической фермы", "storage": "Хранить в холодильнике", "shelf_life": "10 дней", "cooking": "Супы, салаты, гарниры", "location": "Григориополь" },
  { "id": 3, "name": "Тыква", "price": 30, "type": "vegetables", "season": ["Осень","Зима"], "inSeason": true, "method": "Биодинамические", "image": "img/product/tikva.jpg", "farmer": "Сергей Дорош", "farmer_info": "Фермерское хозяйство «Золотая осень»", "storage": "В сухом прохладном месте", "shelf_life": "30 дней", "cooking": "Супы, запеканки, десерты", "location": "Дубоссарский район" },
  { "id": 4, "name": "Молоко", "price": 15, "type": "dairy", "season": ["Весна","Лето","Осень","Зима"], "inSeason": true, "method": "Органические", "image": "img/product/milk.jpg", "farmer": "Анна Василенко", "farmer_info": "Свежие молочные продукты от семейной фермы", "storage": "Хранить в холодильнике 0–6°C", "shelf_life": "5 дней", "cooking": "Пить, готовить каши, выпечку", "location": "Григориополь" },
  { "id": 5, "name": "Сыр", "price": 80, "type": "dairy", "season": ["Весна","Лето","Осень","Зима"], "inSeason": true, "method": "Органические", "image": "img/product/sir.jpg", "farmer": "Анна Василенко", "farmer_info": "Органический сыр с фермы", "storage": "В холодильнике", "shelf_life": "7 дней", "cooking": "Сырная тарелка, выпечка, паста", "location": "Григориополь" },
  { "id": 6, "name": "Йогурт", "price": 18, "type": "dairy", "season": ["Весна","Лето","Осень","Зима"], "inSeason": true, "method": "Без пестицидов", "image": "img/product/yogyrt.jpg", "farmer": "Алексей Литвин", "farmer_info": "Натуральные йогурты без добавок", "storage": "Хранить в холодильнике", "shelf_life": "5 дней", "cooking": "Пить или добавлять в смузи", "location": "Каменский район" },
  { "id": 7, "name": "Куриное мясо", "price": 55, "type": "meat", "season": ["Весна","Лето","Осень","Зима"], "inSeason": true, "method": "Биодинамические", "image": "img/product/chicken.jpg", "farmer": "Сергей Дорош", "farmer_info": "Органическое мясо кур", "storage": "Хранить в холодильнике", "shelf_life": "3 дня", "cooking": "Жарить, варить, запекать", "location": "Дубоссарский район" },
  { "id": 8, "name": "Говядина", "price": 110, "type": "meat", "season": ["Весна","Лето","Осень","Зима"], "inSeason": true, "method": "Биодинамические", "image": "img/product/govyadina.jpg", "farmer": "Сергей Дорош", "farmer_info": "Натуральная говядина без гормонов", "storage": "Хранить в морозильнике", "shelf_life": "3 дня", "cooking": "Стейки, тушение, супы", "location": "Дубоссарский район" },
  { "id": 9, "name": "Свинина", "price": 90, "type": "meat", "season": ["Весна","Лето","Осень","Зима"], "inSeason": true, "method": "Органические", "image": "img/product/svininf.jpg", "farmer": "Мария Иванчук", "farmer_info": "Органическая свинина", "storage": "Хранить в холодильнике или морозильнике", "shelf_life": "3 дня", "cooking": "Жаркое, запекание, супы", "location": "Слободзейский район" },
  { "id": 10, "name": "Яйца 10 шт.", "price": 35, "type": "eggs", "season": ["Весна","Лето","Осень","Зима"], "inSeason": true, "method": "Без пестицидов", "image": "img/product/egg.jpg", "farmer": "Алексей Литвин", "farmer_info": "Яйца от кур свободного выгула", "storage": "В холодильнике", "shelf_life": "14 дней", "cooking": "Варёные, выпечка", "location": "Каменский район" },
  { "id": 11, "name": "Бананы", "price": 22, "type": "fruits", "season": ["Зима"], "inSeason": true, "method": "Органические", "image": "img/product/banani.jpg", "farmer": "Импортные фермы", "farmer_info": "Органические бананы", "storage": "Комнатная температура", "shelf_life": "7 дней", "cooking": "Смузи, свежие", "location": "Импорт" },
  { "id": 12, "name": "Клубника", "price": 55, "type": "fruits", "season": ["Весна","Лето"], "inSeason": true, "method": "Без пестицидов", "image": "img/product/klybnika.jpg", "farmer": "Алексей Литвин", "farmer_info": "Экологическая клубника", "storage": "В холодильнике", "shelf_life": "3 дня", "cooking": "Свежая, варенье", "location": "Каменский район" },
  { "id": 13, "name": "Помидоры", "price": 28, "type": "vegetables", "season": ["Лето","Осень","Зима"], "inSeason": true, "method": "Без пестицидов", "image": "img/product/tomato.jpg", "farmer": "Иван Петров", "farmer_info": "Органические томаты", "storage": "В холодильнике", "shelf_life": "7 дней", "cooking": "Салаты, соусы", "location": "Тираспольский район" },
  { "id": 14, "name": "Огурцы", "price": 22, "type": "vegetables", "season": ["Лето","Осень","Зима"], "inSeason": true, "method": "Без пестицидов", "image": "img/product/ogyrzi.jpg", "farmer": "Иван Петров", "farmer_info": "Без пестицидов", "storage": "В холодильнике", "shelf_life": "7 дней", "cooking": "Салаты", "location": "Тираспольский район" },
  { "id": 15, "name": "Мёд", "price": 95, "type": "honey", "season": ["Лето","Осень"], "inSeason": true, "method": "Без пестицидов", "image": "img/product/med.jpg", "farmer": "Алексей Литвин", "farmer_info": "Натуральный мёд", "storage": "Прохладное место", "shelf_life": "1 год", "cooking": "Чай, десерты", "location": "Каменский район" },
  { "id": 16, "name": "Картофель", "price": 12, "type": "vegetables", "season": ["Лето","Осень","Зима"], "inSeason": true, "method": "Органические", "image": "img/product/kartofel.jpg", "farmer": "Мария Иванчук", "farmer_info": "Органический картофель", "storage": "Прохладное место", "shelf_life": "14 дней", "cooking": "Жарка, варка", "location": "Слободзейский район" },
  { "id": 17, "name": "Лук", "price": 8, "type": "vegetables", "season": ["Осень","Зима"], "inSeason": true, "method": "Биодинамические", "image": "img/product/luk.jpg", "farmer": "Сергей Дорош", "farmer_info": "Органический лук", "storage": "Сухое место", "shelf_life": "30 дней", "cooking": "Соусы, супы", "location": "Дубоссарский район" },
  { "id": 18, "name": "Чеснок", "price": 14, "type": "vegetables", "season": ["Осень","Зима"], "inSeason": true, "method": "Биодинамические", "image": "img/product/chesnok.jpg", "farmer": "Сергей Дорош", "farmer_info": "Органический чеснок", "storage": "Сухое место", "shelf_life": "60 дней", "cooking": "Приправы", "location": "Дубоссарский район" },
  { "id": 19, "name": "Малина", "price": 70, "type": "fruits", "season": ["Лето"], "inSeason": true, "method": "Органические", "image": "img/product/malina.jpg", "farmer": "Мария Иванчук", "farmer_info": "Без химии", "storage": "В холодильнике", "shelf_life": "3 дня", "cooking": "Десерты", "location": "Слободзейский район" },
  { "id": 20, "name": "Черника", "price": 80, "type": "fruits", "season": ["Лето"], "inSeason": true, "method": "Органические", "image": "img/product/chernika.jpg", "farmer": "Мария Иванчук", "farmer_info": "Лесные ягоды", "storage": "В холодильнике", "shelf_life": "5 дней", "cooking": "Смузи", "location": "Слободзейский район" },
  { "id": 21, "name": "Капуста", "price": 15, "type": "vegetables", "season": ["Осень","Зима"], "inSeason": true, "method": "Без пестицидов", "image": "img/product/kapysta.jpg", "farmer": "Иван Петров", "farmer_info": "Органическая капуста", "storage": "В холодильнике", "shelf_life": "14 дней", "cooking": "Тушение", "location": "Тираспольский район" },
  { "id": 22, "name": "Брокколи", "price": 35, "type": "vegetables", "season": ["Весна","Лето","Осень"], "inSeason": true, "method": "Без пестицидов", "image": "img/product/brokolli.jpg", "farmer": "Иван Петров", "farmer_info": "Свежая брокколи", "storage": "В холодильнике", "shelf_life": "7 дней", "cooking": "Запекание", "location": "Тираспольский район" },
  { "id": 23, "name": "Перец", "price": 32, "type": "vegetables", "season": ["Лето"], "inSeason": true, "method": "Без пестицидов", "image": "img/product/perez.jpg", "farmer": "Иван Петров", "farmer_info": "Сладкий перец", "storage": "В холодильнике", "shelf_life": "7 дней", "cooking": "Салаты", "location": "Тираспольский район" },
  { "id": 24, "name": "Киви", "price": 30, "type": "fruits", "season": ["Зима"], "inSeason": true, "method": "Биодинамические", "image": "img/product/kivi.jpg", "farmer": "Сергей Дорош", "farmer_info": "Органические киви", "storage": "Комнатная температура", "shelf_life": "14 дней", "cooking": "Свежие", "location": "Дубоссарский район" },
  { "id": 25, "name": "Грецкий орех", "price": 120, "type": "nuts", "season": ["Осень","Зима"], "inSeason": true, "method": "Биодинамические", "image": "img/product/orex.jpg", "farmer": "Сергей Дорош", "farmer_info": "Орехи премиум-класса", "storage": "Сухое место", "shelf_life": "6 месяцев", "cooking": "Выпечка", "location": "Дубоссарский район" }
]
